board_memory.v
module board_memory (clk, rst, read_en, write_en, cell_index, data_in, data_out, board_flat);

input clk, rst, read_en, write_en;
input [6:0] cell_index;
input [3:0] data_in;
output reg [3:0] data_out;
output [323:0] board_flat; // This is the flattened version of the 9x9 sudoku board
integer k;

reg [3:0] board [0:80]; // 9x9 Sudoku Solver

always @(posedge clk or negedge rst) begin
  if(rst) begin
    for(k = 0; k < 81; k = k +1) begin
      board[k] <= 4'b0000;
    end
  end else begin
    if (write_en) begin
        board[cell_index] <= data_in;
    end else begin
        data_out <= board[cell_index]; 
    end
  end
end
  
genvar index;
generate 
  for(index = 0; index < 81; index = index + 1) begin: flatten_loop
    assign board_flat[index*4 +: 4] = board[index];
  end
endgenerate

endmodule

Main Code/board_memory_tb.v
`timescale 1ns/1ns
`include "board_memory.v"

module board_memory_tb; 

reg clk, rst, read_en, write_en;
reg [6:0] cell_index;
reg [3:0] data_in;
wire [3:0] data_out;
wire [323:0] board_flat;

board_memory uut (clk, rst, read_en, write_en, cell_index, data_in, data_out, board_flat);

always #5 clk = ~clk;

initial begin
    $dumpfile("board_memory.vcd");
    $dumpvars(0, board_memory_tb);

    $monitor("clk: %0b || rst: %0b || read_en: %0b || write_en: %0b || data_in: %0d || cell_index: %0d || data_out: %0d", clk, rst, read_en, write_en, data_in, cell_index, data_out);

    clk = 0;
    rst = 1;
    #8 rst = 0;

    // Write Phase
    #2  write_en = 1; data_in = 1; cell_index = 3;
    #10 write_en = 1; data_in = 6; cell_index = 23;
    #10 write_en = 1; data_in = 4; cell_index = 30;
    #10 write_en = 0;

    // Read Phase
    #5  read_en = 1; cell_index = 3;
    #10 read_en = 1; cell_index = 23;
    #10 read_en = 1; cell_index = 30;
    #10 $finish;
    
end
endmodule

board_memory.vcd
$date
	Sat Aug 09 20:20:39 2025
$end
$version
	Icarus Verilog
$end
$timescale
	1ns
$end
$scope module board_memory_tb $end
$var wire 4 ! data_out [3:0] $end
$var wire 324 " board_flat [323:0] $end
$var reg 7 # cell_index [6:0] $end
$var reg 1 $ clk $end
$var reg 4 % data_in [3:0] $end
$var reg 1 & read_en $end
$var reg 1 ' rst $end
$var reg 1 ( write_en $end
$scope module uut $end
$var wire 7 ) cell_index [6:0] $end
$var wire 1 $ clk $end
$var wire 4 * data_in [3:0] $end
$var wire 1 & read_en $end
$var wire 1 ' rst $end
$var wire 1 ( write_en $end
$var wire 324 + board_flat [323:0] $end
$var reg 4 , data_out [3:0] $end
$var integer 32 - k [31:0] $end
$scope begin flatten_loop[0] $end
$var parameter 2 . index $end
$upscope $end
$scope begin flatten_loop[1] $end
$var parameter 2 / index $end
$upscope $end
$scope begin flatten_loop[2] $end
$var parameter 3 0 index $end
$upscope $end
$scope begin flatten_loop[3] $end
$var parameter 3 1 index $end
$upscope $end
$scope begin flatten_loop[4] $end
$var parameter 4 2 index $end
$upscope $end
$scope begin flatten_loop[5] $end
$var parameter 4 3 index $end
$upscope $end
$scope begin flatten_loop[6] $end
$var parameter 4 4 index $end
$upscope $end
$scope begin flatten_loop[7] $end
$var parameter 4 5 index $end
$upscope $end
$scope begin flatten_loop[8] $end
$var parameter 5 6 index $end
$upscope $end
$scope begin flatten_loop[9] $end
$var parameter 5 7 index $end
$upscope $end
$scope begin flatten_loop[10] $end
$var parameter 5 8 index $end
$upscope $end
$scope begin flatten_loop[11] $end
$var parameter 5 9 index $end
$upscope $end
$scope begin flatten_loop[12] $end
$var parameter 5 : index $end
$upscope $end
$scope begin flatten_loop[13] $end
$var parameter 5 ; index $end
$upscope $end
$scope begin flatten_loop[14] $end
$var parameter 5 < index $end
$upscope $end
$scope begin flatten_loop[15] $end
$var parameter 5 = index $end
$upscope $end
$scope begin flatten_loop[16] $end
$var parameter 6 > index $end
$upscope $end
$scope begin flatten_loop[17] $end
$var parameter 6 ? index $end
$upscope $end
$scope begin flatten_loop[18] $end
$var parameter 6 @ index $end
$upscope $end
$scope begin flatten_loop[19] $end
$var parameter 6 A index $end
$upscope $end
$scope begin flatten_loop[20] $end
$var parameter 6 B index $end
$upscope $end
$scope begin flatten_loop[21] $end
$var parameter 6 C index $end
$upscope $end
$scope begin flatten_loop[22] $end
$var parameter 6 D index $end
$upscope $end
$scope begin flatten_loop[23] $end
$var parameter 6 E index $end
$upscope $end
$scope begin flatten_loop[24] $end
$var parameter 6 F index $end
$upscope $end
$scope begin flatten_loop[25] $end
$var parameter 6 G index $end
$upscope $end
$scope begin flatten_loop[26] $end
$var parameter 6 H index $end
$upscope $end
$scope begin flatten_loop[27] $end
$var parameter 6 I index $end
$upscope $end
$scope begin flatten_loop[28] $end
$var parameter 6 J index $end
$upscope $end
$scope begin flatten_loop[29] $end
$var parameter 6 K index $end
$upscope $end
$scope begin flatten_loop[30] $end
$var parameter 6 L index $end
$upscope $end
$scope begin flatten_loop[31] $end
$var parameter 6 M index $end
$upscope $end
$scope begin flatten_loop[32] $end
$var parameter 7 N index $end
$upscope $end
$scope begin flatten_loop[33] $end
$var parameter 7 O index $end
$upscope $end
$scope begin flatten_loop[34] $end
$var parameter 7 P index $end
$upscope $end
$scope begin flatten_loop[35] $end
$var parameter 7 Q index $end
$upscope $end
$scope begin flatten_loop[36] $end
$var parameter 7 R index $end
$upscope $end
$scope begin flatten_loop[37] $end
$var parameter 7 S index $end
$upscope $end
$scope begin flatten_loop[38] $end
$var parameter 7 T index $end
$upscope $end
$scope begin flatten_loop[39] $end
$var parameter 7 U index $end
$upscope $end
$scope begin flatten_loop[40] $end
$var parameter 7 V index $end
$upscope $end
$scope begin flatten_loop[41] $end
$var parameter 7 W index $end
$upscope $end
$scope begin flatten_loop[42] $end
$var parameter 7 X index $end
$upscope $end
$scope begin flatten_loop[43] $end
$var parameter 7 Y index $end
$upscope $end
$scope begin flatten_loop[44] $end
$var parameter 7 Z index $end
$upscope $end
$scope begin flatten_loop[45] $end
$var parameter 7 [ index $end
$upscope $end
$scope begin flatten_loop[46] $end
$var parameter 7 \ index $end
$upscope $end
$scope begin flatten_loop[47] $end
$var parameter 7 ] index $end
$upscope $end
$scope begin flatten_loop[48] $end
$var parameter 7 ^ index $end
$upscope $end
$scope begin flatten_loop[49] $end
$var parameter 7 _ index $end
$upscope $end
$scope begin flatten_loop[50] $end
$var parameter 7 ` index $end
$upscope $end
$scope begin flatten_loop[51] $end
$var parameter 7 a index $end
$upscope $end
$scope begin flatten_loop[52] $end
$var parameter 7 b index $end
$upscope $end
$scope begin flatten_loop[53] $end
$var parameter 7 c index $end
$upscope $end
$scope begin flatten_loop[54] $end
$var parameter 7 d index $end
$upscope $end
$scope begin flatten_loop[55] $end
$var parameter 7 e index $end
$upscope $end
$scope begin flatten_loop[56] $end
$var parameter 7 f index $end
$upscope $end
$scope begin flatten_loop[57] $end
$var parameter 7 g index $end
$upscope $end
$scope begin flatten_loop[58] $end
$var parameter 7 h index $end
$upscope $end
$scope begin flatten_loop[59] $end
$var parameter 7 i index $end
$upscope $end
$scope begin flatten_loop[60] $end
$var parameter 7 j index $end
$upscope $end
$scope begin flatten_loop[61] $end
$var parameter 7 k index $end
$upscope $end
$scope begin flatten_loop[62] $end
$var parameter 7 l index $end
$upscope $end
$scope begin flatten_loop[63] $end
$var parameter 7 m index $end
$upscope $end
$scope begin flatten_loop[64] $end
$var parameter 8 n index $end
$upscope $end
$scope begin flatten_loop[65] $end
$var parameter 8 o index $end
$upscope $end
$scope begin flatten_loop[66] $end
$var parameter 8 p index $end
$upscope $end
$scope begin flatten_loop[67] $end
$var parameter 8 q index $end
$upscope $end
$scope begin flatten_loop[68] $end
$var parameter 8 r index $end
$upscope $end
$scope begin flatten_loop[69] $end
$var parameter 8 s index $end
$upscope $end
$scope begin flatten_loop[70] $end
$var parameter 8 t index $end
$upscope $end
$scope begin flatten_loop[71] $end
$var parameter 8 u index $end
$upscope $end
$scope begin flatten_loop[72] $end
$var parameter 8 v index $end
$upscope $end
$scope begin flatten_loop[73] $end
$var parameter 8 w index $end
$upscope $end
$scope begin flatten_loop[74] $end
$var parameter 8 x index $end
$upscope $end
$scope begin flatten_loop[75] $end
$var parameter 8 y index $end
$upscope $end
$scope begin flatten_loop[76] $end
$var parameter 8 z index $end
$upscope $end
$scope begin flatten_loop[77] $end
$var parameter 8 { index $end
$upscope $end
$scope begin flatten_loop[78] $end
$var parameter 8 | index $end
$upscope $end
$scope begin flatten_loop[79] $end
$var parameter 8 } index $end
$upscope $end
$scope begin flatten_loop[80] $end
$var parameter 8 ~ index $end
$upscope $end
$upscope $end
$upscope $end
$enddefinitions $end
$comment Show the parameter values. $end
$dumpall
b1010000 ~
b1001111 }
b1001110 |
b1001101 {
b1001100 z
b1001011 y
b1001010 x
b1001001 w
b1001000 v
b1000111 u
b1000110 t
b1000101 s
b1000100 r
b1000011 q
b1000010 p
b1000001 o
b1000000 n
b111111 m
b111110 l
b111101 k
b111100 j
b111011 i
b111010 h
b111001 g
b111000 f
b110111 e
b110110 d
b110101 c
b110100 b
b110011 a
b110010 `
b110001 _
b110000 ^
b101111 ]
b101110 \
b101101 [
b101100 Z
b101011 Y
b101010 X
b101001 W
b101000 V
b100111 U
b100110 T
b100101 S
b100100 R
b100011 Q
b100010 P
b100001 O
b100000 N
b11111 M
b11110 L
b11101 K
b11100 J
b11011 I
b11010 H
b11001 G
b11000 F
b10111 E
b10110 D
b10101 C
b10100 B
b10011 A
b10010 @
b10001 ?
b10000 >
b1111 =
b1110 <
b1101 ;
b1100 :
b1011 9
b1010 8
b1001 7
b1000 6
b111 5
b110 4
b101 3
b100 2
b11 1
b10 0
b1 /
b0 .
$end
#0
$dumpvars
bx -
bx ,
bx +
bx *
bx )
x(
1'
x&
bx %
0$
bx #
bx "
bx !
$end
#5
b0 "
b0 +
b1010001 -
1$
#8
0'
#10
b11 #
b11 )
b1 %
b1 *
1(
0$
#15
b1000000000000 "
b1000000000000 +
1$
#20
0$
b10111 #
b10111 )
b110 %
b110 *
#25
b11000000000000000000000000000000000000000000000000000000000000000000000000000000001000000000000 "
b11000000000000000000000000000000000000000000000000000000000000000000000000000000001000000000000 +
1$
#30
0$
b11110 #
b11110 )
b100 %
b100 *
#35
b100000000000000000000000000011000000000000000000000000000000000000000000000000000000000000000000000000000000001000000000000 "
b100000000000000000000000000011000000000000000000000000000000000000000000000000000000000000000000000000000000001000000000000 +
1$
#40
0$
0(
#45
b1 !
b1 ,
1$
b11 #
b11 )
1&
#50
0$
#55
b110 !
b110 ,
1$
b10111 #
b10111 )
#60
0$
#65
b100 !
b100 ,
1$
b11110 #
b11110 )
