board_memory.v
module board_memory (clk, rst, read_en, write_en, cell_index, data_in, data_out);

input clk, rst, read_en, write_en;
input [6:0] cell_index;
input [3:0] data_in;
output reg [3:0] data_out;

always @(posedge clk or negedge rst) begin
  if(rst) begin
    read_en <= 0;
    write_en <=0;
  end
end
    
endmodule

board_memory_tb.v
`timescale 1ns/1ns
`include "board_memory.v"

module board_memory_tb; 

reg clk, rst, read_en, write_en;
reg [6:0] cell_index;
reg [3:0] data_in;
wire [3:0] data_out;

board_memory uut (clk, rst, read_en, write_en, cell_index, data_in, data_out);

always #5 clk = ~clk;

initial begin
    $dumpfile("board_memory.vcd");
    $dumpvars(0, board_memory_tb);

    $monitor("clk: %0b || rst: %0b || read_en: %0b || write_en: %0b || data_in: %0d || cell_index: %0d || data_out: %0d", clk, rst, read_en, write_en, data_in, cell_index, data_out);

    clk = 0;
    rst = 1;
    #8 rst = 0;

    // Write Phase
    #2  write_en = 1; data_in = 1; cell_index = 3;
    #10 write_en = 1; data_in = 6; cell_index = 23;
    #10 write_en = 1; data_in = 4; cell_index = 30;
    #10 write_en = 0;

    // Read Phase
    #5  read_en = 1; cell_index = 3;
    #10 read_en = 1; cell_index = 23;
    #10 read_en = 1; cell_index = 30;
    #10 $finish;
    
end
endmodule

board_memory.vcd
$date
	Wed Aug 06 02:42:13 2025
$end
$version
	Icarus Verilog
$end
$timescale
	1ns
$end
$scope module board_memory_tb $end
$var wire 4 ! data_out [3:0] $end
$var reg 7 " cell_index [6:0] $end
$var reg 1 # clk $end
$var reg 4 $ data_in [3:0] $end
$var reg 1 % read_en $end
$var reg 1 & rst $end
$var reg 1 ' write_en $end
$scope module uut $end
$var wire 7 ( cell_index [6:0] $end
$var wire 1 # clk $end
$var wire 4 ) data_in [3:0] $end
$var wire 1 % read_en $end
$var wire 1 & rst $end
$var wire 1 ' write_en $end
$var reg 4 * data_out [3:0] $end
$upscope $end
$upscope $end
$enddefinitions $end
$comment Show the parameter values. $end
$dumpall
$end
#0
$dumpvars
bx *
bx )
bx (
x'
1&
x%
bx $
0#
bx "
bx !
$end
#5
b0 !
b0 *
1#
#8
bx !
bx *
0&
#10
b11 "
b11 (
b1 $
b1 )
1'
0#
#15
1#
#20
0#
b10111 "
b10111 (
b110 $
b110 )
#25
1#
#30
0#
b11110 "
b11110 (
b100 $
b100 )
#35
1#
#40
0#
0'
#45
b1 !
b1 *
1#
b11 "
b11 (
1%
#50
0#
#55
b110 !
b110 *
1#
b10111 "
b10111 (
#60
0#
#65
b100 !
b100 *
1#
b11110 "
b11110 (
