constraint_checker.v
module constraint_checker (num_to_place, cell_index, valid, board_flat);

input [3:0] num_to_place;
input [6:0] cell_index;
input [323:0] board_flat;
output reg valid;     
reg [3:0] cell_val;

integer row, col;
integer index;
integer start_row, start_col;
integer i, j;

always @(*) begin

    row = (cell_index) / 9;
    col = (cell_index) % 9;
    valid = 1;

//  For ROW checking
    for (integer i = 0; i < 9; i = i + 1) begin
        index = row*9 + i;
        cell_val = board_flat[index*4 +: 4];
        if((cell_val == num_to_place) && index!= cell_index) begin
            valid = 0;
        end
    end

//  For COLUMN checking
    for (integer i = 0; i < 9; i = i + 1) begin
        index = i*9 + col;
        cell_val = board_flat[(index*4) +: 4];
        if((cell_val == num_to_place) && index!= cell_index) begin
            valid = 0;
        end
    end

    start_row = (row / 3)*3;
    start_col = (col / 3)*3;

//  For 3x3 box checking
    for (i = start_row; i < start_row + 3; i = i + 1) begin
        for (j = start_col; j < start_col + 3; j = j + 1) begin
            index = i*9 + j;
            cell_val = board_flat[(index*4) +: 4];
            if((cell_val == num_to_place) && index!= cell_index) begin
                valid = 0;
        end
    end
end
end
endmodule

constraint_checker_tb.v
`timescale 1ns/1ns
`include "constraint_checker.v"

module constraint_checker_tb;

reg [3:0] num_to_place;
reg [6:0] cell_index;
reg [323:0] board_flat;
wire valid;

constraint_checker uut (num_to_place, cell_index, valid, board_flat);

integer r, c;

initial begin 
    $dumpfile("constrain_checker.vcd");
    $dumpvars(0, constraint_checker_tb);

    #5 board_flat = {324{1'b0}}; 
    num_to_place = 4'd5; 
    cell_index = 7'd0; 
    print_board();

    #5 board_flat[4*3 +: 4] = 4'd5; 
    num_to_place = 4'd5; 
    cell_index = 7'd0; 
    print_board();

    #5 board_flat = {324{1'b0}};
    board_flat[4*(0 + 9*2) +: 4] = 4'd5;
    num_to_place = 4'd5; 
    cell_index = 7'd0; 
    print_board();

    #5 board_flat = {324{1'b0}};
    board_flat[4*(1 + 9*1) +: 4] = 4'd5;
    num_to_place = 4'd5; 
    cell_index = 7'd0; 
    print_board();

    #10 $finish;
end

task print_board;
    begin
        $display("Time: %0t || num_to_place: %0d || cell_index: %0d || valid: %0b", 
                  $time, num_to_place, cell_index, valid);
        for (r = 0; r < 9; r = r + 1) begin
            for (c = 0; c < 9; c = c + 1) begin
                $write("%0d ", board_flat[((r*9 + c)*4) +: 4]);
            end
            $write("\n");
        end
        $display("");
    end
endtask

    
endmodule

System generated code files/constrain_checker.vcd
$date
	Wed Aug 13 17:09:29 2025
$end
$version
	Icarus Verilog
$end
$timescale
	1ns
$end
$scope module constraint_checker_tb $end
$var wire 1 ! valid $end
$var reg 324 " board_flat [323:0] $end
$var reg 7 # cell_index [6:0] $end
$var reg 4 $ num_to_place [3:0] $end
$var integer 32 % c [31:0] $end
$var integer 32 & r [31:0] $end
$scope module uut $end
$var wire 324 ' board_flat [323:0] $end
$var wire 7 ( cell_index [6:0] $end
$var wire 4 ) num_to_place [3:0] $end
$var reg 4 * cell_val [3:0] $end
$var reg 1 ! valid $end
$var integer 32 + col [31:0] $end
$var integer 32 , i [31:0] $end
$var integer 32 - index [31:0] $end
$var integer 32 . j [31:0] $end
$var integer 32 / row [31:0] $end
$var integer 32 0 start_col [31:0] $end
$var integer 32 1 start_row [31:0] $end
$upscope $end
$scope task print_board $end
$upscope $end
$upscope $end
$enddefinitions $end
$comment Show the parameter values. $end
$dumpall
$end
#0
$dumpvars
bx 1
bx 0
bx /
bx .
bx -
bx ,
bx +
bx *
bx )
bx (
bx '
bx &
bx %
bx $
bx #
bx "
x!
$end
#5
b11 .
b0 0
b0 1
b0 *
b10100 -
b11 ,
1!
b0 +
b0 /
b0 #
b0 (
b101 $
b101 )
b0 "
b0 '
#6
b1001 %
b1001 &
#11
b11 .
0!
b0 *
b10100 -
b11 ,
b101000000000000 "
b101000000000000 '
#12
b1001 %
b1001 &
#17
b11 .
b0 *
b10100 -
b11 ,
0!
b101000000000000000000000000000000000000000000000000000000000000000000000000 "
b101000000000000000000000000000000000000000000000000000000000000000000000000 '
#18
b1001 %
b1001 &
#23
b0 *
b11 .
b10100 -
b11 ,
0!
b1010000000000000000000000000000000000000000 "
b1010000000000000000000000000000000000000000 '
#24
b1001 %
b1001 &
